aio_confluent_kafka/__init__.py
aio_confluent_kafka/_consumer.py
aio_confluent_kafka/_producer.py
aio_confluent_kafka-0.0.1.dist-info/METADATA
aio_confluent_kafka-0.0.1.dist-info/WHEEL
aio_confluent_kafka-0.0.1.dist-info/top_level.txt
aio_confluent_kafka-0.0.1.dist-info/RECORD
